README.rst
protobuf_setuptools.py
setup.py
protobuf_setuptools.egg-info/PKG-INFO
protobuf_setuptools.egg-info/SOURCES.txt
protobuf_setuptools.egg-info/dependency_links.txt
protobuf_setuptools.egg-info/entry_points.txt
protobuf_setuptools.egg-info/top_level.txt