Metadata-Version: 1.0
Name: protobuf-setuptools
Version: 0.1.1
Summary: setuptools build_proto command
Home-page: https://github.com/pupssman/protobuf-setuptools
Author: Ivan Kalinin
Author-email: pupssman@yandex-team.ru
License: Apache License, Version 2.0
Platform: UNKNOWN
